apppy/sb/__init__.py
apppy/sb/auth.py
apppy/sb/auth_test.py
apppy/sb/db.py
apppy/sb/fs.py
apppy/sb/fs_fixtures.py
apppy/sb/fs_test.py
apppy/sb/fs_unit_test.py
apppy/sb/logflare.py
apppy/sb/migrations.py
apppy/sb/identity/__init__.py
apppy/sb/identity/errors.py
apppy_sb-0.23.2.dist-info/METADATA
apppy_sb-0.23.2.dist-info/WHEEL
apppy_sb-0.23.2.dist-info/RECORD
