Metadata-Version: 2.4
Name: apppy-sb
Version: 0.23.2
Summary: Supabase integrations for server development
Project-URL: Homepage, https://github.com/spals/apppy
Author: Tim Kral
License: MIT
Classifier: License :: OSI Approved :: MIT License
Classifier: Programming Language :: Python :: 3
Requires-Python: >=3.11
Requires-Dist: apppy-auth>=0.23.2
Requires-Dist: apppy-db>=0.23.2
Requires-Dist: apppy-env>=0.23.2
Requires-Dist: apppy-fs>=0.23.2
Requires-Dist: apppy-generic>=0.23.2
Requires-Dist: apppy-logger>=0.23.2
Requires-Dist: apppy-queues>=0.23.2
Requires-Dist: argon2-cffi==25.1.0
Requires-Dist: fastapi-lifespan-manager==0.1.4
Requires-Dist: requests==2.32.4
Requires-Dist: supabase==2.15.3
Requires-Dist: tuspy==1.1.0
